orion_common/__init__.py
orion_common/example.py
orion_common/orion_authentication/__init__.py
orion_common/orion_core/__init__.py
orion_common/orion_core/admin/BaseAdmin.py
orion_common/orion_core/admin/__init__.py
orion_common/orion_core/authentication/__init__.py
orion_common/orion_core/authentication/authentication.py
orion_common/orion_core/authentication/throttling.py
orion_common/orion_core/backends/UsernameBackend.py
orion_common/orion_core/backends/__init__.py
orion_common/orion_core/decorators/__init__.py
orion_common/orion_core/decorators/super_user_required.py
orion_common/orion_core/dependencies/__init__.py
orion_common/orion_core/dependencies/parler_rest/__init__.py
orion_common/orion_core/dependencies/parler_rest/fields.py
orion_common/orion_core/dependencies/parler_rest/serializers.py
orion_common/orion_core/dependencies/parler_rest/utils.py
orion_common/orion_core/middleware/DisableCSRFMiddleware.py
orion_common/orion_core/middleware/__init__.py
orion_common/orion_core/models/Base.py
orion_common/orion_core/models/__init__.py
orion_common/orion_core/pagination/Pagination.py
orion_common/orion_core/pagination/__init__.py
orion_common/orion_core/permission/ActivePermission.py
orion_common/orion_core/permission/SuperOrReadPermission.py
orion_common/orion_core/permission/SuperPermission.py
orion_common/orion_core/permission/__init__.py
orion_common/orion_core/renderers/JsonResponse.py
orion_common/orion_core/renderers/__init__.py
orion_common/orion_core/scripts/__init__.py
orion_common/orion_core/scripts/dump.py
orion_common/orion_core/validators/__init__.py
orion_common/orion_core/validators/password_strength_validate.py
orion_common/scripts/__init__.py
orion_common/scripts/dump.py
orion_common/static/admin/css/autocomplete.css
orion_common/static/admin/css/base.css
orion_common/static/admin/css/changelists.css
orion_common/static/admin/css/dashboard.css
orion_common/static/admin/css/fonts.css
orion_common/static/admin/css/forms.css
orion_common-1.2.1.dist-info/METADATA
orion_common-1.2.1.dist-info/WHEEL
orion_common-1.2.1.dist-info/top_level.txt
orion_common-1.2.1.dist-info/RECORD
