Metadata-Version: 2.1
Name: orion-common
Version: 1.2.1
Summary: A small example package
Home-page: https://edugonmor.autogen.ovh
Author: edugonmor
Author-email: edugonmor@outlook.com
License: UNKNOWN
Project-URL: Bug Tracker, https://github.com/pypa/sampleproject/issues
Platform: UNKNOWN
Classifier: Programming Language :: Python :: 3
Classifier: License :: OSI Approved :: MIT License
Classifier: Operating System :: OS Independent
Requires-Python: >=3.9.0
Requires-Dist: amqp (==5.0.9)
Requires-Dist: asgiref (==3.5.0)
Requires-Dist: billiard (==3.6.4.0)
Requires-Dist: braintree (==4.13.1)
Requires-Dist: celery (==5.2.3)
Requires-Dist: certifi (==2021.10.8)
Requires-Dist: cffi (==1.15.0)
Requires-Dist: charset-normalizer (==2.0.10)
Requires-Dist: click (==8.0.3)
Requires-Dist: click-didyoumean (==0.3.0)
Requires-Dist: click-plugins (==1.1.1)
Requires-Dist: click-repl (==0.2.0)
Requires-Dist: cryptography (==36.0.1)
Requires-Dist: Deprecated (==1.2.13)
Requires-Dist: Django (==4.0.1)
Requires-Dist: django-cors-headers (==3.11.0)
Requires-Dist: django-extensions (==3.1.5)
Requires-Dist: django-filter (==21.1)
Requires-Dist: django-parler (==2.3)
Requires-Dist: django-redis (==5.2.0)
Requires-Dist: django-rosetta (==0.9.8)
Requires-Dist: django-taggit (==2.1.0)
Requires-Dist: djangorestframework (==3.13.1)
Requires-Dist: djangorestframework-simplejwt (==5.0.0)
Requires-Dist: idna (==3.3)
Requires-Dist: kombu (==5.2.3)
Requires-Dist: localflavor (==1.9)
Requires-Dist: packaging (==21.3)
Requires-Dist: Pillow (==9.0.0)
Requires-Dist: polib (==1.1.1)
Requires-Dist: prompt-toolkit (==3.0.26)
Requires-Dist: psycopg2-binary (==2.9.3)
Requires-Dist: pycparser (==2.21)
Requires-Dist: PyJWT (==2.3.0)
Requires-Dist: pyOpenSSL (==21.0.0)
Requires-Dist: pyparsing (==3.0.7)
Requires-Dist: pytz (==2021.3)
Requires-Dist: PyYAML (==6.0)
Requires-Dist: redis (==4.1.2)
Requires-Dist: requests (==2.27.1)
Requires-Dist: six (==1.16.0)
Requires-Dist: sqlparse (==0.4.2)
Requires-Dist: urllib3 (==1.26.8)
Requires-Dist: vine (==5.0.0)
Requires-Dist: wcwidth (==0.2.5)
Requires-Dist: Werkzeug (==2.0.2)
Requires-Dist: wrapt (==1.13.3)
